{
  "version": "1.0.0",
  "restore": {
    "projectUniqueName": "C:\\Users\\tcornwell\\datacomp\\GiveAShitBackend\\GiveAShitBackend.csproj",
    "projectName": "GiveAShitBackend",
    "projectPath": "C:\\Users\\tcornwell\\datacomp\\GiveAShitBackend\\GiveAShitBackend.csproj",
    "outputPath": "C:\\Users\\tcornwell\\datacomp\\GiveAShitBackend\\obj\\",
    "projectStyle": "PackageReference",
    "originalTargetFrameworks": [
      "netcoreapp2.0"
    ],
    "frameworks": {
      "netcoreapp2.0": {
        "projectReferences": {}
      }
    }
  },
  "frameworks": {
    "netcoreapp2.0": {
      "dependencies": {
        "Microsoft.NETCore.App": {
          "target": "Package",
          "version": "2.0.0"
        },
        "Microsoft.AspNetCore.All": {
          "target": "Package",
          "version": "2.0.0"
        }
      }
    }
  }
}